web_bricks/__init__.py
web_bricks/acesss_logger.py
web_bricks/chain_forward_resolver.py
web_bricks/component.py
web_bricks/index_locator.py
web_bricks/locator_extractor.py
web_bricks/resolve_result.py
web_bricks/resolver.py
web_bricks/resolver_interface.py
web_bricks/safety_error.py
web_bricks/utils.py
web_bricks/web_bricks_config.py
web_bricks-0.1.3.dist-info/LICENSE
web_bricks-0.1.3.dist-info/METADATA
web_bricks-0.1.3.dist-info/WHEEL
web_bricks-0.1.3.dist-info/top_level.txt
web_bricks-0.1.3.dist-info/RECORD
