Metadata-Version: 2.1
Name: web-bricks
Version: 0.1.3
Summary: Page Object constructor for UI automation
Home-page: https://github.com/2gis-test-labs/web-bricks
Author: 2GIS Test Labs
Author-email: test-labs@2gis.ru
License: Apache-2.0
Classifier: License :: OSI Approved :: Apache Software License
Classifier: Programming Language :: Python :: 3.8
Classifier: Programming Language :: Python :: 3.9
Classifier: Programming Language :: Python :: 3.10
Requires-Python: >=3.8.0
License-File: LICENSE
Requires-Dist: rtry (<1.5.0,>=1.3.0)
